docs/conf.py
omnixai/__init__.py
omnixai/data/__init__.py
omnixai/data/base.py
omnixai/data/image.py
omnixai/data/multi_inputs.py
omnixai/data/tabular.py
omnixai/data/text.py
omnixai/data/timeseries.py
omnixai/deployment/__init__.py
omnixai/deployment/bentoml/__init__.py
omnixai/deployment/bentoml/omnixai.py
omnixai/explainers/__init__.py
omnixai/explainers/base.py
omnixai/explainers/data/__init__.py
omnixai/explainers/data/auto.py
omnixai/explainers/data/chi_square.py
omnixai/explainers/data/correlation.py
omnixai/explainers/data/imbalance.py
omnixai/explainers/data/mutual_info.py
omnixai/explainers/nlp/__init__.py
omnixai/explainers/nlp/auto.py
omnixai/explainers/nlp/agnostic/__init__.py
omnixai/explainers/nlp/agnostic/l2x.py
omnixai/explainers/nlp/agnostic/lime.py
omnixai/explainers/nlp/agnostic/shap.py
omnixai/explainers/nlp/counterfactual/__init__.py
omnixai/explainers/nlp/counterfactual/polyjuice.py
omnixai/explainers/nlp/specific/__init__.py
omnixai/explainers/nlp/specific/ig.py
omnixai/explainers/prediction/__init__.py
omnixai/explainers/prediction/auto.py
omnixai/explainers/ranking/__init__.py
omnixai/explainers/ranking/agnostic/__init__.py
omnixai/explainers/ranking/agnostic/permutation.py
omnixai/explainers/ranking/agnostic/validity.py
omnixai/explainers/ranking/counterfactual/__init__.py
omnixai/explainers/ranking/counterfactual/mace.py
omnixai/explainers/tabular/__init__.py
omnixai/explainers/tabular/auto.py
omnixai/explainers/tabular/base.py
omnixai/explainers/tabular/agnostic/__init__.py
omnixai/explainers/tabular/agnostic/ale.py
omnixai/explainers/tabular/agnostic/bias.py
omnixai/explainers/tabular/agnostic/gpt.py
omnixai/explainers/tabular/agnostic/lime.py
omnixai/explainers/tabular/agnostic/pdp.py
omnixai/explainers/tabular/agnostic/permutation.py
omnixai/explainers/tabular/agnostic/sensitivity.py
omnixai/explainers/tabular/agnostic/shap.py
omnixai/explainers/tabular/agnostic/shap_global.py
omnixai/explainers/tabular/agnostic/L2X/__init__.py
omnixai-1.3.1.dist-info/LICENSE
omnixai-1.3.1.dist-info/METADATA
omnixai-1.3.1.dist-info/WHEEL
omnixai-1.3.1.dist-info/top_level.txt
omnixai-1.3.1.dist-info/RECORD
