Metadata-Version: 2.1
Name: omnixai
Version: 1.3.1
Summary: OmniXAI: An Explainable AI Toolbox
Home-page: https://github.com/salesforce/omnixai
Author: Wenzhuo Yang, Hung Le, Tanmay Shivprasad Laud, Silvio Savarese, Steven C.H. Hoi
License: 3-Clause BSD
Keywords: XAI Explainable AI Explanation
Requires-Python: >=3.7,<4
License-File: LICENSE
Requires-Dist: numpy (<1.24,>=1.17)
Requires-Dist: pandas (>=1.1.0)
Requires-Dist: scikit-learn (<1.2,>=0.24)
Requires-Dist: scipy (>=1.5.0)
Requires-Dist: scikit-image (>=0.17.2)
Requires-Dist: matplotlib
Requires-Dist: pillow (<10.0)
Requires-Dist: lime
Requires-Dist: shap (>=0.40.0)
Requires-Dist: SALib
Requires-Dist: hnswlib (>=0.5.0)
Requires-Dist: dill
Requires-Dist: tqdm
Requires-Dist: wheel
Requires-Dist: packaging
Requires-Dist: ipython (>=8.10.0)
Requires-Dist: tabulate
Requires-Dist: statsmodels (>=0.10.1)
Requires-Dist: openai
Provides-Extra: all
Requires-Dist: plotly (>=4) ; extra == 'all'
Requires-Dist: dash (>=2.0) ; extra == 'all'
Requires-Dist: dash-bootstrap-components (>=1.0) ; extra == 'all'
Requires-Dist: jupyter-dash (>=0.4) ; extra == 'all'
Requires-Dist: torch (>=1.7) ; extra == 'all'
Requires-Dist: torchvision (>=0.8.1) ; extra == 'all'
Requires-Dist: opencv-python-headless (>=4.4) ; extra == 'all'
Requires-Dist: nltk (>=3.4.5) ; extra == 'all'
Requires-Dist: polyjuice-nlp ; extra == 'all'
Requires-Dist: bentoml (>=1.0.0) ; extra == 'all'
Provides-Extra: bentoml
Requires-Dist: bentoml (>=1.0.0) ; extra == 'bentoml'
Provides-Extra: nlp
Requires-Dist: nltk (>=3.4.5) ; extra == 'nlp'
Requires-Dist: polyjuice-nlp ; extra == 'nlp'
Provides-Extra: plot
Requires-Dist: plotly (>=4) ; extra == 'plot'
Requires-Dist: dash (>=2.0) ; extra == 'plot'
Requires-Dist: dash-bootstrap-components (>=1.0) ; extra == 'plot'
Requires-Dist: jupyter-dash (>=0.4) ; extra == 'plot'
Provides-Extra: vision
Requires-Dist: torch (>=1.7) ; extra == 'vision'
Requires-Dist: torchvision (>=0.8.1) ; extra == 'vision'
Requires-Dist: opencv-python-headless (>=4.4) ; extra == 'vision'
